[
  {
    "word": "clarify",
    "meaning": "明らかにする",
    "example": "He clarified the point.",
    "example_jp": "彼はその点を明らかにした。"
  },
  {
    "word": "smash",
    "meaning": "粉々に砕く",
    "example": "He smashed the glass.",
    "example_jp": "彼はガラスを粉々に砕いた。"
  },
  {
    "word": "mourn",
    "meaning": "悲しむ",
    "example": "They mourned his death.",
    "example_jp": "彼らは彼の死を悲しんだ。"
  },
  {
    "word": "summon",
    "meaning": "呼ぶ",
    "example": "She summoned him to the office.",
    "example_jp": "彼女は彼をオフィスに呼び出した。"
  },
  {
    "word": "shatter",
    "meaning": "粉々にする",
    "example": "The window shattered.",
    "example_jp": "窓が粉々に割れた。"
  },
  {
    "word": "linger",
    "meaning": "残る",
    "example": "The smell lingered.",
    "example_jp": "その匂いが残った。"
  },
  {
    "word": "lament",
    "meaning": "嘆く",
    "example": "She lamented the loss.",
    "example_jp": "彼女はその喪失を嘆いた。"
  },
  {
    "word": "endowed",
    "meaning": "恵まれる",
    "example": "He is endowed with talent.",
    "example_jp": "彼は才能に恵まれている。"
  },
  {
    "word": "rejoice",
    "meaning": "喜ぶ",
    "example": "They rejoiced at the news.",
    "example_jp": "彼らはその知らせに喜んだ。"
  },
  {
    "word": "allocate",
    "meaning": "配分する",
    "example": "They allocated money to the project.",
    "example_jp": "彼らはそのプロジェクトに資金を配分した。"
  },
  {
    "word": "slap",
    "meaning": "ピシャリと打つ",
    "example": "She slapped his hand.",
    "example_jp": "彼女は彼の手をピシャリと打った。"
  },
  {
    "word": "contend",
    "meaning": "主張する",
    "example": "He contended that he was right.",
    "example_jp": "彼は自分が正しいと主張した。"
  },
  {
    "word": "swear",
    "meaning": "誓う",
    "example": "He swore to keep the secret.",
    "example_jp": "彼はその秘密を守ると誓った。"
  },
  {
    "word": "discern",
    "meaning": "識別する",
    "example": "I discerned a small change.",
    "example_jp": "私はわずかな変化を識別した。"
  },
  {
    "word": "degrade",
    "meaning": "悪化させる",
    "example": "Pollution degrades the environment.",
    "example_jp": "汚染は環境を悪化させる。"
  },
  {
    "word": "erect",
    "meaning": "築く",
    "example": "They erected a new building.",
    "example_jp": "彼らは新しい建物を建てた。"
  },
  {
    "word": "testify",
    "meaning": "証言する",
    "example": "He testified in court.",
    "example_jp": "彼は法廷で証言した。"
  },
  {
    "word": "spur",
    "meaning": "駆りたてる",
    "example": "The victory spurred him on.",
    "example_jp": "その勝利が彼を駆り立てた。"
  },
  {
    "word": "roam",
    "meaning": "歩き回る",
    "example": "They roamed the streets.",
    "example_jp": "彼らは通りを歩き回った。"
  },
  {
    "word": "frown",
    "meaning": "まゆをひそめる",
    "example": "She frowned at the noise.",
    "example_jp": "彼女はその騒音に眉をひそめた。"
  },
  {
    "word": "lure",
    "meaning": "呼び込む",
    "example": "The ad lured customers.",
    "example_jp": "その広告は客を呼び込んだ。"
  },
  {
    "word": "defy",
    "meaning": "逆らう",
    "example": "He defied the rule.",
    "example_jp": "彼はその規則に逆らった。"
  },
  {
    "word": "stroll",
    "meaning": "ぶらつく",
    "example": "They strolled in the park.",
    "example_jp": "彼らは公園をぶらついた。"
  },
  {
    "word": "rattle",
    "meaning": "がたがた鳴らす",
    "example": "The door rattled in the wind.",
    "example_jp": "風でドアががたがた鳴った。"
  },
  {
    "word": "reconcile",
    "meaning": "調和させる",
    "example": "They reconciled their differences.",
    "example_jp": "彼らは意見の相違を調和させた。"
  },
  {
    "word": "blur",
    "meaning": "ぼやかす",
    "example": "Tears blurred her vision.",
    "example_jp": "涙で彼女の視界がぼやけた。"
  },
  {
    "word": "soothe",
    "meaning": "なだめる",
    "example": "Music soothed her mind.",
    "example_jp": "音楽が彼女の心をなだめた。"
  },
  {
    "word": "impair",
    "meaning": "低下させる",
    "example": "The injury impaired his vision.",
    "example_jp": "そのけがが彼の視力を低下させた。"
  },
  {
    "word": "comply",
    "meaning": "従う",
    "example": "They complied with the law.",
    "example_jp": "彼らは法律に従った。"
  },
  {
    "word": "pierce",
    "meaning": "穴をあける",
    "example": "He pierced the paper.",
    "example_jp": "彼は紙に穴をあけた。"
  },
  {
    "word": "stumble",
    "meaning": "つまずく",
    "example": "He stumbled on a rock.",
    "example_jp": "彼は石につまずいた。"
  },
  {
    "word": "hinder",
    "meaning": "さまたげる",
    "example": "The rain hindered progress.",
    "example_jp": "雨が進行を妨げた。"
  },
  {
    "word": "mock",
    "meaning": "あざける",
    "example": "They mocked his idea.",
    "example_jp": "彼らは彼の考えをあざけった。"
  },
  {
    "word": "embody",
    "meaning": "具現する",
    "example": "The statue embodies freedom.",
    "example_jp": "その像は自由を具現している。"
  },
  {
    "word": "stalk",
    "meaning": "忍び寄る",
    "example": "The cat stalked the bird.",
    "example_jp": "猫は鳥に忍び寄った。"
  },
  {
    "word": "proclaim",
    "meaning": "宣言する",
    "example": "He proclaimed his victory.",
    "example_jp": "彼は自分の勝利を宣言した。"
  },
  {
    "word": "applaud",
    "meaning": "拍手する",
    "example": "The audience applauded.",
    "example_jp": "観客は拍手した。"
  },
  {
    "word": "inflict",
    "meaning": "与える",
    "example": "The storm inflicted damage.",
    "example_jp": "その嵐は被害を与えた。"
  },
  {
    "word": "merge",
    "meaning": "合併する",
    "example": "The two companies merged.",
    "example_jp": "その2社は合併した。"
  },
  {
    "word": "evacuated",
    "meaning": "避難した",
    "example": "They evacuated the building.",
    "example_jp": "彼らは建物から避難した。"
  },
  {
    "word": "undone",
    "meaning": "元に戻る",
    "example": "The plan came undone.",
    "example_jp": "その計画は元に戻ってしまった。"
  },
  {
    "word": "poke",
    "meaning": "突く",
    "example": "He poked the fire.",
    "example_jp": "彼は火を突いた。"
  },
  {
    "word": "haunted",
    "meaning": "つきまとわれる",
    "example": "He was haunted by memories.",
    "example_jp": "彼は記憶に取りつかれていた。"
  },
  {
    "word": "adhere",
    "meaning": "固く守る",
    "example": "They adhered to the rules.",
    "example_jp": "彼らは規則を固く守った。"
  },
  {
    "word": "compile",
    "meaning": "まとめる",
    "example": "They compiled the data.",
    "example_jp": "彼らはデータをまとめた。"
  },
  {
    "word": "wither",
    "meaning": "しぼむ",
    "example": "The flowers withered.",
    "example_jp": "花がしおれた。"
  },
  {
    "word": "stun",
    "meaning": "びっくりさせる",
    "example": "The news stunned him.",
    "example_jp": "そのニュースは彼を驚かせた。"
  },
  {
    "word": "choke",
    "meaning": "のどがつまる",
    "example": "He choked on the food.",
    "example_jp": "彼は食べ物でのどを詰まらせた。"
  },
  {
    "word": "deteriorate",
    "meaning": "悪化する",
    "example": "The situation deteriorated.",
    "example_jp": "状況は悪化した。"
  },
  {
    "word": "dump",
    "meaning": "捨てる",
    "example": "They dumped the trash.",
    "example_jp": "彼らはごみを捨てた。"
  }
]