[
  {
    "word": "a large number of",
    "meaning": "たくさんの",
    "example": "A large number of people come.",
    "example_jp": "たくさんの人々が来る。"
  },
  {
    "word": "a series of",
    "meaning": "一連の",
    "example": "We watch a series of movies.",
    "example_jp": "私たちは一連の映画を見る。"
  },
  {
    "word": "a series of",
    "meaning": "一続きの",
    "example": "A series of events happens.",
    "example_jp": "一続きの出来事が起こる。"
  },
  {
    "word": "as long as",
    "meaning": "…である限り",
    "example": "You can stay as long as you want.",
    "example_jp": "あなたが望む限り、滞在してもよい。"
  },
  {
    "word": "as soon as",
    "meaning": "…するとすぐに",
    "example": "Call me as soon as you arrive.",
    "example_jp": "到着するとすぐに私に電話をください。"
  },
  {
    "word": "had better",
    "meaning": "…するべきだ",
    "example": "You had better study now.",
    "example_jp": "あなたは今勉強するべきだ。"
  },
  {
    "word": "more and more",
    "meaning": "ますます多くの",
    "example": "More and more students join.",
    "example_jp": "ますます多くの学生が参加する。"
  },
  {
    "word": "not at all",
    "meaning": "まったく〜ではない",
    "example": "I am not at all tired.",
    "example_jp": "私はまったく疲れていない。"
  },
  {
    "word": "not A but B",
    "meaning": "AではなくてB",
    "example": "I choose not A but B.",
    "example_jp": "私はAではなくてBを選ぶ。"
  },
  {
    "word": "the first time",
    "meaning": "初めて…したとき",
    "example": "I met him the first time in Tokyo.",
    "example_jp": "私は東京で初めて彼に会った。"
  },
  {
    "word": "when it comes to",
    "meaning": "〜のこととなると",
    "example": "When it comes to math, he is great.",
    "example_jp": "数学のこととなると、彼は素晴らしい。"
  },
  {
    "word": "parent",
    "meaning": "親",
    "example": "My parent is kind.",
    "example_jp": "私の親は親切だ。"
  },
  {
    "word": "husband",
    "meaning": "夫",
    "example": "Her husband is a teacher.",
    "example_jp": "彼女の夫は教師だ。"
  },
  {
    "word": "wife",
    "meaning": "妻",
    "example": "His wife is busy today.",
    "example_jp": "彼の妻は今日忙しい。"
  },
  {
    "word": "kid",
    "meaning": "子供",
    "example": "The kid is playing outside.",
    "example_jp": "その子供は外で遊んでいる。"
  },
  {
    "word": "twin",
    "meaning": "双子（の１人）",
    "example": "She is a twin.",
    "example_jp": "彼女は双子（の１人）だ。"
  },
  {
    "word": "relative",
    "meaning": "親戚",
    "example": "I visit my relatives.",
    "example_jp": "私は自分の親戚を訪ねる。"
  },
  {
    "word": "cousin",
    "meaning": "いとこ",
    "example": "My cousin lives in Osaka.",
    "example_jp": "私のいとこは大阪に住んでいる。"
  },
  {
    "word": "ancestor",
    "meaning": "先祖",
    "example": "We learn about our ancestors.",
    "example_jp": "私たちは自分たちの先祖について学ぶ。"
  },
  {
    "word": "job",
    "meaning": "仕事",
    "example": "I get a new job.",
    "example_jp": "私は新しい仕事を得る。"
  },
  {
    "word": "work",
    "meaning": "仕事",
    "example": "I have a lot of work.",
    "example_jp": "私はたくさんの仕事がある。"
  },
  {
    "word": "occupation",
    "meaning": "職業",
    "example": "His occupation is doctor.",
    "example_jp": "彼の職業は医者だ。"
  },
  {
    "word": "career",
    "meaning": "職業",
    "example": "She starts her career in music.",
    "example_jp": "彼女は音楽の職業（キャリア）を始める。"
  },
  {
    "word": "businesss",
    "meaning": "仕事",
    "example": "He starts a new business.",
    "example_jp": "彼は新しい仕事を始める。"
  },
  {
    "word": "businesss",
    "meaning": "商売",
    "example": "She runs a small business.",
    "example_jp": "彼女は小さな商売を営んでいる。"
  },
  {
    "word": "interview",
    "meaning": "面接",
    "example": "I have an interview today.",
    "example_jp": "私は今日面接がある。"
  },
  {
    "word": "hire",
    "meaning": "雇う",
    "example": "They hire new workers.",
    "example_jp": "彼らは新しい労働者を雇う。"
  },
  {
    "word": "retire",
    "meaning": "退職する",
    "example": "He retires at 60.",
    "example_jp": "彼は60歳で退職する。"
  },
  {
    "word": "retire",
    "meaning": "引退する",
    "example": "She retires from tennis.",
    "example_jp": "彼女はテニスから引退する。"
  },
  {
    "word": "clerk",
    "meaning": "店員",
    "example": "The clerk helps me.",
    "example_jp": "その店員は私を手伝ってくれる。"
  },
  {
    "word": "officer",
    "meaning": "警官",
    "example": "The officer stops the car.",
    "example_jp": "その警官は車を止める。"
  },
  {
    "word": "engineer",
    "meaning": "技師",
    "example": "He is an engineer.",
    "example_jp": "彼は技師だ。"
  },
  {
    "word": "artist",
    "meaning": "芸術家",
    "example": "She is a famous artist.",
    "example_jp": "彼女は有名な芸術家だ。"
  },
  {
    "word": "director",
    "meaning": "監督",
    "example": "The director makes the movie.",
    "example_jp": "その監督が映画を作る。"
  },
  {
    "word": "actor",
    "meaning": "俳優",
    "example": "He is a good actor.",
    "example_jp": "彼は良い俳優だ。"
  },
  {
    "word": "nurse",
    "meaning": "看護師",
    "example": "The nurse is kind.",
    "example_jp": "その看護師は親切だ。"
  },
  {
    "word": "secretary",
    "meaning": "秘書",
    "example": "The secretary writes emails.",
    "example_jp": "その秘書はメールを書く。"
  },
  {
    "word": "agent",
    "meaning": "代行業者",
    "example": "The agent helps us.",
    "example_jp": "その代行業者は私たちを助けてくれる。"
  },
  {
    "word": "civil",
    "meaning": "民間の",
    "example": "He works in civil service.",
    "example_jp": "彼は民間（公務）の仕事で働いている。"
  },
  {
    "word": "mayor",
    "meaning": "市長",
    "example": "The mayor speaks today.",
    "example_jp": "市長が今日話す。"
  },
  {
    "word": "chairperson",
    "meaning": "議長",
    "example": "The chairperson leads the meeting.",
    "example_jp": "議長が会議を進行させる。"
  },
  {
    "word": "professor",
    "meaning": "教授",
    "example": "The professor teaches history.",
    "example_jp": "その教授は歴史を教えている。"
  },
  {
    "word": "principal",
    "meaning": "校長",
    "example": "The principal talks to students.",
    "example_jp": "校長が学生たちに話す。"
  },
  {
    "word": "expert",
    "meaning": "専門家",
    "example": "She is an expert in science.",
    "example_jp": "彼女は科学の専門家だ。"
  },
  {
    "word": "leader",
    "meaning": "指導者",
    "example": "He is the team leader.",
    "example_jp": "彼はチームの指導者だ。"
  },
  {
    "word": "queen",
    "meaning": "女王",
    "example": "The queen visits the city.",
    "example_jp": "女王がその都市を訪れる。"
  },
  {
    "word": "prince",
    "meaning": "王子",
    "example": "The prince is young.",
    "example_jp": "その王子は若い。"
  },
  {
    "word": "royal",
    "meaning": "国王の",
    "example": "They live in a royal palace.",
    "example_jp": "彼らは国王の宮殿に住んでいる。"
  },
  {
    "word": "slave",
    "meaning": "奴隷",
    "example": "The story is about a slave.",
    "example_jp": "その物語は奴隷についてのものだ。"
  },
  {
    "word": "hall",
    "meaning": "会館",
    "example": "We meet in the hall.",
    "example_jp": "私たちは会館で会う。"
  },
  {
    "word": "office",
    "meaning": "事務所",
    "example": "I work in an office.",
    "example_jp": "私は事務所で働いている。"
  },
  {
    "word": "office",
    "meaning": "会社",
    "example": "This is a big office.",
    "example_jp": "これは大きな会社だ。"
  },
  {
    "word": "bank",
    "meaning": "銀行",
    "example": "I go to the bank.",
    "example_jp": "私は銀行に行く。"
  },
  {
    "word": "apartment",
    "meaning": "アパート",
    "example": "She lives in an apartment.",
    "example_jp": "彼女はアパートに住んでいる。"
  }
]